certigen/__init__.py
certigen/__main__.py
certigen/generator.py
certigen/utils.py
certigen-1.1.0.dist-info/licenses/LICENSE
certigen-1.1.0.dist-info/METADATA
certigen-1.1.0.dist-info/WHEEL
certigen-1.1.0.dist-info/entry_points.txt
certigen-1.1.0.dist-info/top_level.txt
certigen-1.1.0.dist-info/RECORD
