Metadata-Version: 2.4
Name: certigen
Version: 1.1.0
Summary: Automatic certificate generator with OCR-based placeholder detection (no external dependencies)
Author-email: Nakul Desai <nakuldesai2006@gmail.com>
License: MIT
Project-URL: Homepage, https://github.com/bravetiger01/certigen
Project-URL: Documentation, https://github.com/bravetiger01/certigen#readme
Project-URL: Repository, https://github.com/bravetiger01/certigen
Project-URL: Issues, https://github.com/bravetiger01/certigen/issues
Keywords: certificate,generator,ocr,automation,pdf
Classifier: Development Status :: 4 - Beta
Classifier: Intended Audience :: Developers
Classifier: Intended Audience :: Education
Classifier: License :: OSI Approved :: MIT License
Classifier: Operating System :: OS Independent
Classifier: Programming Language :: Python :: 3
Classifier: Programming Language :: Python :: 3.8
Classifier: Programming Language :: Python :: 3.9
Classifier: Programming Language :: Python :: 3.10
Classifier: Programming Language :: Python :: 3.11
Classifier: Programming Language :: Python :: 3.12
Classifier: Topic :: Multimedia :: Graphics
Classifier: Topic :: Office/Business
Requires-Python: >=3.8
License-File: LICENSE
Requires-Dist: Pillow>=9.0.0
Requires-Dist: pandas>=1.3.0
Requires-Dist: numpy>=1.20.0
Requires-Dist: openpyxl>=3.0.0
Requires-Dist: rapidocr-onnxruntime>=1.3.0
Provides-Extra: cloud
Requires-Dist: boto3>=1.26.0; extra == "cloud"
Requires-Dist: google-api-python-client>=2.0.0; extra == "cloud"
Requires-Dist: google-auth>=2.0.0; extra == "cloud"
Provides-Extra: all
Requires-Dist: certigen[cloud]; extra == "all"
Dynamic: license-file
